aiochris/__init__.py
aiochris/enums.py
aiochris/errors.py
aiochris/examples.md
aiochris/home.md
aiochris/types.py
aiochris/client/__init__.py
aiochris/client/admin.py
aiochris/client/anon.py
aiochris/client/authed.py
aiochris/client/base.py
aiochris/client/from_chrs.py
aiochris/client/normal.py
aiochris/link/__init__.py
aiochris/link/collection_client.py
aiochris/link/http.py
aiochris/link/linked.py
aiochris/link/metaprog.py
aiochris/models/__init__.py
aiochris/models/collection_links.py
aiochris/models/data.py
aiochris/models/logged_in.py
aiochris/models/public.py
aiochris/util/__init__.py
aiochris/util/search.py
aiochris-0.10.0.dist-info/METADATA
aiochris-0.10.0.dist-info/WHEEL
aiochris-0.10.0.dist-info/licenses/LICENSE
aiochris-0.10.0.dist-info/RECORD
