Metadata-Version: 2.3
Name: aiochris
Version: 0.10.0
Summary: ChRIS client built on aiohttp
Author-email: Jennings Zhang <jennings.zhang@childrens.harvard.edu>, FNNDSC <dev@babyMRI.org>
License-File: LICENSE
Requires-Python: >=3.11
Requires-Dist: aiohttp>=3.9.5
Requires-Dist: async-property>=0.2.2
Requires-Dist: pyserde>=0.19.3
Requires-Dist: yarl>=1.9.4
